baish_assistant/__init__.py
baish_assistant/main.py
baish_assistant-0.1.2.dist-info/METADATA
baish_assistant-0.1.2.dist-info/WHEEL
baish_assistant-0.1.2.dist-info/entry_points.txt
baish_assistant-0.1.2.dist-info/licenses/LICENSE
baish_assistant-0.1.2.dist-info/RECORD
