Metadata-Version: 2.4
Name: baish-assistant
Version: 0.1.2
Summary: Convert natural language instructions to bash commands using Ollama
Project-URL: Homepage, https://github.com/tcsenpai/baish
Project-URL: Repository, https://github.com/tcsenpai/baish
Project-URL: Bug Reports, https://github.com/tcsenpai/baish/issues
Project-URL: Documentation, https://github.com/tcsenpai/baish#readme
Author-email: tcsenpai <tcsenpai@discus.sh>
License: MIT
License-File: LICENSE
Keywords: ai,bash,cli,nlp,ollama,terminal
Classifier: Development Status :: 4 - Beta
Classifier: Intended Audience :: Developers
Classifier: Intended Audience :: System Administrators
Classifier: License :: OSI Approved :: MIT License
Classifier: Operating System :: OS Independent
Classifier: Programming Language :: Python :: 3
Classifier: Programming Language :: Python :: 3.8
Classifier: Programming Language :: Python :: 3.9
Classifier: Programming Language :: Python :: 3.10
Classifier: Programming Language :: Python :: 3.11
Classifier: Programming Language :: Python :: 3.12
Classifier: Topic :: Software Development :: Libraries :: Python Modules
Classifier: Topic :: System :: System Shells
Classifier: Topic :: Utilities
Requires-Python: >=3.8
Requires-Dist: click>=8.0.0
Requires-Dist: python-dotenv>=1.0.0
Requires-Dist: requests>=2.31.0
Requires-Dist: rich>=13.0.0
Provides-Extra: dev
Requires-Dist: black>=23.0.0; extra == 'dev'
Requires-Dist: build>=1.0.0; extra == 'dev'
Requires-Dist: pytest>=7.0.0; extra == 'dev'
Requires-Dist: ruff>=0.1.0; extra == 'dev'
Requires-Dist: twine>=4.0.0; extra == 'dev'
